{
  "683246a74073e586d112af9f": {
    "$type": "RealismMod.Ammo, RealismMod",
    "Name": "6.5x48mm Creedmoor Norma Match",
    "Damage": 72,
    "PenetrationPower": 69,
    "LoyaltyLevel": 1,
    "BasePriceModifier": 1,
    "ItemID": "683246a74073e586d112af9f",
    "InitialSpeed": 908,
    "BulletMassGram": 14.95,
    "ammoRec": 41,
    "ammoAccr": -16,
    "ArmorDamage": 1.15,
    "HeatFactor": 1.32,
    "HeavyBleedingDelta": 0.06,
    "LightBleedingDelta": 0.16,
    "DurabilityBurnModificator": 1.44,
    "BallisticCoeficient": 0.41,
    "MalfMisfireChance": 0.006,
    "MisfireChance": 0.013,
    "MalfFeedChance": 0.013
  },
  "68325a63730b17c69ee176eb": {
    "$type": "RealismMod.Ammo, RealismMod",
    "Name": "6.5x48mm Creedmoor HPBT Match",
    "Damage": 74,
    "PenetrationPower": 63,
    "LoyaltyLevel": 1,
    "BasePriceModifier": 1,
    "ItemID": "68325a63730b17c69ee176eb",
    "InitialSpeed": 856,
    "BulletMassGram": 7.41,
    "ammoRec": 29,
    "ammoAccr": -14,
    "ArmorDamage": 1.155,
    "HeatFactor": 1.22,
    "HeavyBleedingDelta": 0.08,
    "LightBleedingDelta": 0.29,
    "DurabilityBurnModificator": 1.2,
    "BallisticCoeficient": 0.33,
    "MalfMisfireChance": 0.014,
    "MisfireChance": 0.007,
    "MalfFeedChance": 0.007
  },
  "6833baea86387d71b68abd6f": {
    "$type": "RealismMod.Ammo, RealismMod",
    "Name": "6.5x48mm Creedmoor Hornady ELD-X",
    "Damage": 103,
    "PenetrationPower": 68,
    "LoyaltyLevel": 1,
    "BasePriceModifier": 1,
    "ItemID": "6833baea86387d71b68abd6f",
    "InitialSpeed": 824,
    "BulletMassGram": 9.49,
    "BallisticCoeficient": 0.44,
    "ammoRec": 19,
    "ammoAccr": -3,
    "ArmorDamage": 1.154,
    "HeatFactor": 1.15,
    "HeavyBleedingDelta": 0.2,
    "LightBleedingDelta": 0.27,
    "DurabilityBurnModificator": 1.28,
    "MalfMisfireChance": 0.004,
    "MisfireChance": 0.008,
    "MalfFeedChance": 0.002
  },
  "6833bae4baa31474639bea7d": {
    "$type": "RealismMod.Ammo, RealismMod",
    "Name": "6.5x48mm Creedmoor Norma AP",
    "Damage": 50,
    "PenetrationPower": 102,
    "LoyaltyLevel": 1,
    "BasePriceModifier": 1,
    "ItemID": "6833bae4baa31474639bea7d",
    "InitialSpeed": 888,
    "BulletMassGram": 12.54,
    "BallisticCoeficient": 0.45,
    "ammoRec": 45,
    "ammoAccr": -12,
    "ArmorDamage": 1.174,
    "HeatFactor": 1.38,
    "HeavyBleedingDelta": -0.05,
    "LightBleedingDelta": 0.18,
    "DurabilityBurnModificator": 1.62,
    "MalfMisfireChance": 0.0122,
    "MisfireChance": 0.0094,
    "MalfFeedChance": 0.0112
  },
  "6833ba38a1c9ff155c04e56f": {
    "$type": "RealismMod.Ammo, RealismMod",
    "Name": "6.5x48mm Creedmoor Terminal Ascent",
    "Damage": 92,
    "PenetrationPower": 66,
    "LoyaltyLevel": 1,
    "BasePriceModifier": 1,
    "ItemID": "6833ba38a1c9ff155c04e56f",
    "InitialSpeed": 923,
    "BulletMassGram": 12.26,
    "BallisticCoeficient": 0.43,
    "ammoRec": 25,
    "ammoAccr": -7,
    "ArmorDamage": 1.142,
    "HeatFactor": 1.33,
    "HeavyBleedingDelta": 0.08,
    "LightBleedingDelta": 0.34,
    "DurabilityBurnModificator": 1.2,
    "MalfMisfireChance": 0.011,
    "MisfireChance": 0.007,
    "MalfFeedChance": 0.007
  },
  "6833b8cb54aa764b2deefdfe": {
    "$type": "RealismMod.Ammo, RealismMod",
    "Name": "6.5x48mm Creedmoor SIG Venari SP",
    "Damage": 97,
    "PenetrationPower": 45,
    "LoyaltyLevel": 1,
    "BasePriceModifier": 1,
    "ItemID": "6833b8cb54aa764b2deefdfe",
    "InitialSpeed": 857,
    "BulletMassGram": 9.29,
    "ammoRec": 12,
    "ammoAccr": 3,
    "ArmorDamage": 1.18,
    "HeatFactor": 1.32,
    "HeavyBleedingDelta": 0.24,
    "LightBleedingDelta": 0.3,
    "DurabilityBurnModificator": 1.23,
    "BallisticCoeficient": 0.35,
    "MalfMisfireChance": 0.007,
    "MisfireChance": 0.008,
    "MalfFeedChance": 0.007
  },
  "6834e6f28f5570aec23ca0c2": {
    "$type": "RealismMod.Ammo, RealismMod",
    "Name": "6.5x48mm Creedmoor C-HP",
    "Damage": 112,
    "PenetrationPower": 68,
    "LoyaltyLevel": 1,
    "BasePriceModifier": 1,
    "ItemID": "6834e6f28f5570aec23ca0c2",
    "InitialSpeed": 853,
    "BulletMassGram": 11.23,
    "ammoRec": 27,
    "ammoAccr": 4,
    "ArmorDamage": 1.18,
    "HeatFactor": 1.06,
    "HeavyBleedingDelta": 0.24,
    "LightBleedingDelta": 0.26,
    "DurabilityBurnModificator": 1.35,
    "BallisticCoeficient": 0.4,
    "MalfMisfireChance": 0.007,
    "MisfireChance": 0.01,
    "MalfFeedChance": 0.008
  },
  "683d1b69d6f6778f205e9dfd": {
    "$type": "RealismMod.Ammo, RealismMod",
    "Name": "6.8x51mm SIG Venari SP",
    "Damage": 73,
    "PenetrationPower": 42,
    "LoyaltyLevel": 1,
    "BasePriceModifier": 1,
    "ItemID": "683d1b69d6f6778f205e9dfd",
    "InitialSpeed": 949,
    "BulletMassGram": 13.51,
    "ammoRec": 25,
    "ammoAccr": 5,
    "ArmorDamage": 1.15,
    "HeatFactor": 1.11,
    "HeavyBleedingDelta": 0.42,
    "LightBleedingDelta": 0.35,
    "DurabilityBurnModificator": 1.39,
    "BallisticCoeficient": 0.4,
    "MalfMisfireChance": 0.01,
    "MisfireChance": 0.012,
    "MalfFeedChance": 0.01
  },
  "683a1844ac7f29765fc135b2": {
    "$type": "RealismMod.Ammo, RealismMod",
    "Name": "6.8x51mm SIG HiPower",
    "Damage": 70,
    "PenetrationPower": 68,
    "LoyaltyLevel": 1,
    "BasePriceModifier": 1,
    "ItemID": "683a1844ac7f29765fc135b2",
    "InitialSpeed": 730,
    "BulletMassGram": 13.89,
    "ammoRec": 6,
    "ammoAccr": 1,
    "ArmorDamage": 1.147,
    "HeatFactor": 1.08,
    "HeavyBleedingDelta": 0.34,
    "LightBleedingDelta": 0.39,
    "DurabilityBurnModificator": 1.2,
    "BallisticCoeficient": 0.22,
    "MalfMisfireChance": 0.004,
    "MisfireChance": 0.007,
    "MalfFeedChance": 0.007
  },
  "683d1ba7b5a2063de35a8c39": {
    "$type": "RealismMod.Ammo, RealismMod",
    "Name": "8.6 Blackout AP-Subsonic",
    "Damage": 98,
    "PenetrationPower": 104,
    "LoyaltyLevel": 1,
    "BasePriceModifier": 1,
    "ItemID": "683d1ba7b5a2063de35a8c39",
    "InitialSpeed": 874,
    "BulletMassGram": 20.33,
    "ammoRec": 53,
    "ammoAccr": -25,
    "ArmorDamage": 1.17,
    "HeatFactor": 1.61,
    "HeavyBleedingDelta": 0.06,
    "LightBleedingDelta": 0.04,
    "DurabilityBurnModificator": 1.63,
    "BallisticCoeficient": 0.56,
    "MalfMisfireChance": 0.0092,
    "MisfireChance": 0.0108,
    "MalfFeedChance": 0.0098
  },
  "683d1e142cee4317689e75e4": {
    "$type": "RealismMod.Ammo, RealismMod",
    "Name": "8.6 Blackout Copper Solid",
    "Damage": 98,
    "PenetrationPower": 76,
    "LoyaltyLevel": 1,
    "BasePriceModifier": 1,
    "ItemID": "683d1e142cee4317689e75e4",
    "InitialSpeed": 866,
    "BulletMassGram": 15.04,
    "ammoRec": 64,
    "ammoAccr": -22,
    "ArmorDamage": 1.149,
    "HeatFactor": 1.56,
    "HeavyBleedingDelta": 0.15,
    "LightBleedingDelta": 0.27,
    "DurabilityBurnModificator": 1.57,
    "BallisticCoeficient": 0.38,
    "MalfMisfireChance": 0.013,
    "MisfireChance": 0.013,
    "MalfFeedChance": 0.008
  },
  "683d1ec4f7164f4f77ea7a85": {
    "$type": "RealismMod.Ammo, RealismMod",
    "Name": "8.6 Blackout REX Subsonic",
    "Damage": 81,
    "PenetrationPower": 106,
    "LoyaltyLevel": 1,
    "BasePriceModifier": 1,
    "ItemID": "683d1ec4f7164f4f77ea7a85",
    "InitialSpeed": 873,
    "BulletMassGram": 20.9,
    "ammoRec": 41,
    "ammoAccr": -6,
    "ArmorDamage": 1.15,
    "HeatFactor": 1.44,
    "HeavyBleedingDelta": 0.07,
    "LightBleedingDelta": 0.18,
    "DurabilityBurnModificator": 1.33,
    "BallisticCoeficient": 0.58,
    "MalfMisfireChance": 0.01,
    "MisfireChance": 0.008,
    "MalfFeedChance": 0.014
  }
}